{
  "updated_at": "2026-06-17T14:12:03",
  "date": "20260617",
  "patterns": [
    {
      "id": "cp_false_positive_in_theme_repair",
      "name": "主题强修复日中的 CP 假阳性",
      "occurrence_count": 43,
      "dates": [
        "20260609",
        "20260610",
        "20260611",
        "20260612",
        "20260616"
      ],
      "recommendation": "candidate_for_rule_or_weight",
      "note": "Same pattern has repeated at least 3 times; start evaluating rule, weight, or ranking upgrades."
    },
    {
      "id": "theme_cluster_repair",
      "name": "主线簇修复",
      "occurrence_count": 30,
      "dates": [
        "20260528",
        "20260604",
        "20260611",
        "20260612",
        "20260616"
      ],
      "recommendation": "candidate_for_rule_or_weight",
      "note": "Same pattern has repeated at least 3 times; start evaluating rule, weight, or ranking upgrades."
    }
  ]
}